hermesbaby/Kconfig
hermesbaby/Makefile
hermesbaby/__init__.py
hermesbaby/__main__.py
hermesbaby/additional-files-for-out/favicon.ico
hermesbaby/additional-files-for-out/index.html.jinja
hermesbaby/additional-files-for-out/pdfjs.zip
hermesbaby/atlassian-admin/README.md
hermesbaby/atlassian-admin/__init__.py
hermesbaby/atlassian-admin/create-release-tags.py
hermesbaby/atlassian-admin/get_branches.py
hermesbaby/ci/Dockerfile
hermesbaby/ci/README.md
hermesbaby/ci/__init__.py
hermesbaby/ci/parse_config/README.md
hermesbaby/ci/parse_config/__init__.py
hermesbaby/ci/parse_config/__main__.py
hermesbaby/ci/parse_config/parse_config.py
hermesbaby/ci/parse_config/test.py
hermesbaby/ci/run.sh
hermesbaby/ci/setup.sh
hermesbaby/conf.py
hermesbaby/drawio/__init__.py
hermesbaby/drawio/debug/drawio-batch.sh
hermesbaby/drawio/drawio.css
hermesbaby/external_tools.json
hermesbaby/htaccess.yaml
hermesbaby/html_static/custom.css
hermesbaby/loflot/README.md
hermesbaby/loflot/__init__.py
hermesbaby/partly/README.md
hermesbaby/partly/__init__.py
hermesbaby/partly/test.py
hermesbaby/plantuml.config
hermesbaby/pre-post-build/README.md
hermesbaby/pre-post-build/__init__.py
hermesbaby/puppeteer.config.json
hermesbaby/rst-frontmatter/README.md
hermesbaby/rst-frontmatter/__init__.py
hermesbaby/scoopfile-build.json
hermesbaby/tag-anything/.gitignore
hermesbaby/templates/arc42-de/cookiecutter.json
hermesbaby/templates/arc42-de/{{cookiecutter.directory}}/.gitignore
hermesbaby/templates/arc42-de/{{cookiecutter.directory}}/.vscode/keybindings.json
hermesbaby/templates/arc42-de/{{cookiecutter.directory}}/.vscode/settings.json
hermesbaby/templates/arc42-de/{{cookiecutter.directory}}/.vscode/tasks.json
hermesbaby/templates/arc42-de/{{cookiecutter.directory}}/docs/01-Introduction-and-Goals/_figures/quality_goals_iso_25010_2023_de.drawio
hermesbaby/templates/arc42-de/{{cookiecutter.directory}}/docs/01-Introduction-and-Goals/index.md
hermesbaby-2026.1.18.48.dist-info/METADATA
hermesbaby-2026.1.18.48.dist-info/WHEEL
hermesbaby-2026.1.18.48.dist-info/entry_points.txt
hermesbaby-2026.1.18.48.dist-info/licenses/LICENSE.md
hermesbaby-2026.1.18.48.dist-info/RECORD
