Metadata-Version: 2.4
Name: hermesbaby
Version: 2026.1.18.48
Summary: The Software and Systems Engineers' Typewriter
License: MIT for contents used as software, CC BY-SA-4.0 for contents used as method or otherwise
License-File: LICENSE.md
Author: basejumpa
Author-email: alexander.mannwahrenberg@gmail.com
Requires-Python: >=3.12,<4.0
Classifier: License :: Other/Proprietary License
Classifier: Programming Language :: Python :: 3
Classifier: Programming Language :: Python :: 3.12
Classifier: Programming Language :: Python :: 3.13
Classifier: Programming Language :: Python :: 3.14
Requires-Dist: atlassian-python-api (>=3.41.14,<4.0.0)
Requires-Dist: beautifulsoup4 (>=4.12.3,<5.0.0)
Requires-Dist: cookiecutter (>=2.6.0,<3.0.0)
Requires-Dist: gitpython (>=3.1.43,<4.0.0)
Requires-Dist: jupyter-sphinx (>=0.5.3,<0.6.0)
Requires-Dist: kconfiglib (>=14.1.0,<15.0.0)
Requires-Dist: linkify-it-py (>=2.0.3,<3.0.0)
Requires-Dist: mlx-traceability (>=11.7.0,<12.0.0)
Requires-Dist: myst-nb (>=1.1.0,<2.0.0)
Requires-Dist: myst-parser (>=4.0.0,<5.0.0)
Requires-Dist: pandas (>=2.2.2,<3.0.0)
Requires-Dist: pillow (>=10.3.0,<11.0.0)
Requires-Dist: pip-system-certs (>=4.0,<5.0)
Requires-Dist: pyad (>=0.6.0,<0.7.0)
Requires-Dist: pytz (>=2024.1,<2025.0)
Requires-Dist: pywin32 ; sys_platform == "win32"
Requires-Dist: pyyaml (>=6.0.1,<7.0.0)
Requires-Dist: robotframeworklexer (>=1.1,<2.0)
Requires-Dist: setuptools (>=70.0.0)
Requires-Dist: sphinx
Requires-Dist: sphinx-autobuild (>=2024.10.3,<2025.0.0)
Requires-Dist: sphinx-copybutton (>=0.5.2,<0.6.0)
Requires-Dist: sphinx-datatables (>=0.2.1,<0.3.0)
Requires-Dist: sphinx-design (>=0.6.0,<0.7.0)
Requires-Dist: sphinx-material (>=0.0.36,<0.0.37)
Requires-Dist: sphinx-mdinclude (>=0.6.1,<0.7.0)
Requires-Dist: sphinx-needs (>=5.1.0,<6.0.0)
Requires-Dist: sphinx-tags (>=0.3.1,<0.4.0)
Requires-Dist: sphinx-toolbox (>=3.7.0,<4.0.0)
Requires-Dist: sphinxcontrib-bibtex (>=2.6.2,<3.0.0)
Requires-Dist: sphinxcontrib-datatemplates (>=0.11.0,<0.12.0)
Requires-Dist: sphinxcontrib-details-directive (>=0.1.0,<0.2.0)
Requires-Dist: sphinxcontrib-mermaid (>=0.9.2,<0.10.0)
Requires-Dist: sphinxcontrib-plantuml (>=0.29,<0.30)
Requires-Dist: sphinxcontrib-svg2pdfconverter (>=2.0.0,<3.0.0)
Requires-Dist: sphinxcontrib-xlsxtable (>=1.1.1,<2.0.0)
Requires-Dist: sphinxext-rediraffe (>=0.2.7,<0.3.0)
Requires-Dist: typer (>=0.15.1,<0.16.0)
Requires-Dist: tzlocal (>=5.2,<6.0)
Requires-Dist: windows-curses (>=2.3,<3.0) ; sys_platform == "win32"
Project-URL: Homepage, https://github.com/hermesbaby
